CMakeLists.txt
LICENSE.txt
MANIFEST.in
README.md
pyproject.toml
requirements.txt
setup.cfg
setup.py
versioneer.py
distopia/CMakeLists.txt
distopia/__init__.py
distopia/_distopia.pyx
distopia/_version.py
distopia.egg-info/PKG-INFO
distopia.egg-info/SOURCES.txt
distopia.egg-info/dependency_links.txt
distopia.egg-info/requires.txt
distopia.egg-info/top_level.txt
distopia/tests/test_distopia.py
docs/.nojekyll
docs/Doxyfile
docs/Makefile
docs/building_distopia.rst
docs/conf.py
docs/index.rst
docs/make.bat
docs/_static/custom.css
docs/_static/logos/mdanalysis-logo-thin.png
docs/_static/logos/mdanalysis-logo.ico
docs/_templates/footer.html
docs/api/distopia.rst
docs/api/libdistopia.rst
libdistopia/CMakeLists.txt
libdistopia/cmake/ColorOutput.cmake
libdistopia/cmake/FindARM.cmake
libdistopia/cmake/FindAVX.cmake
libdistopia/cmake/FindSSE.cmake
libdistopia/cmake/README.md
libdistopia/compare/anglekernels.h
libdistopia/compare/calc_distances.h
libdistopia/compare/dihedralkernels.h
libdistopia/compare/distancekernels.h
libdistopia/compare/vanilla.cpp
libdistopia/compare/vanilla.h
libdistopia/compare/vectorize_sse.h
libdistopia/libdistopia/include/distopia.h
libdistopia/libdistopia/lib/box.h
libdistopia/libdistopia/lib/calc_bonds.cpp
libdistopia/libdistopia/lib/calc_bonds_dispatch.cpp
libdistopia/libdistopia/lib/calc_bonds_dispatch.h
libdistopia/libdistopia/lib/compiler_hints.h
libdistopia/libdistopia/lib/distances.h
libdistopia/libdistopia/lib/distopia_type_traits.h
libdistopia/libdistopia/lib/simd_dispatch.h
libdistopia/libdistopia/lib/simd_swizzles.h
libdistopia/libdistopia/lib/vector_triple.h
libdistopia/tests/benchmark.cpp
libdistopia/tests/test_fixtures.h
libdistopia/tests/test_matches.cpp
libdistopia/tests/test_utils.h
libdistopia/tests/unit_tests.cpp
libdistopia/tests/googlebench/.clang-format
libdistopia/tests/googlebench/.clang-tidy
libdistopia/tests/googlebench/.gitignore
libdistopia/tests/googlebench/.travis.yml
libdistopia/tests/googlebench/.ycm_extra_conf.py
libdistopia/tests/googlebench/AUTHORS
libdistopia/tests/googlebench/BUILD.bazel
libdistopia/tests/googlebench/CMakeLists.txt
